catnap/__init__.py
catnap/assess.py
catnap/bbox.py
catnap/catmaid_interface.py
catnap/constants.py
catnap/io.py
catnap/navigator.py
catnap/utils.py
catnap/version.py
catnap/view.py
catnap/bin/__init__.py
catnap/bin/assess.py
catnap/bin/create.py
catnap/bin/utils.py
catnap/bin/view.py
catmaid_catnap-0.4.0.dist-info/LICENSE
catmaid_catnap-0.4.0.dist-info/METADATA
catmaid_catnap-0.4.0.dist-info/WHEEL
catmaid_catnap-0.4.0.dist-info/entry_points.txt
catmaid_catnap-0.4.0.dist-info/top_level.txt
catmaid_catnap-0.4.0.dist-info/RECORD
