Metadata-Version: 2.1
Name: catmaid-catnap
Version: 0.4.0
Summary: Experiments working with CATMAID and napari
Home-page: https://github.com/clbarnes/catmaid-catnap
Author: Chris L. Barnes
Author-email: cb619@cam.ac.uk
License: UNKNOWN
Keywords: neuroscience,connectomics,image,graph
Platform: UNKNOWN
Classifier: Development Status :: 3 - Alpha
Classifier: Intended Audience :: Developers
Classifier: License :: OSI Approved :: MIT License
Classifier: Programming Language :: Python :: 3
Classifier: Programming Language :: Python :: 3.7
Classifier: Programming Language :: Python :: 3.8
Classifier: Programming Language :: Python :: 3 :: Only
Requires-Python: >=3.7, <4
Requires-Dist: catpy (>=2020.9.3)
Requires-Dist: coordinates
Requires-Dist: h5py
Requires-Dist: napari[all] (~=0.4.6)
Requires-Dist: numpy
Requires-Dist: pandas
Requires-Dist: scipy
Requires-Dist: scikit-image
Requires-Dist: StrEnum
Requires-Dist: tables
Requires-Dist: tqdm
Requires-Dist: zarr
